connection_helper/__init__.py
connection_helper/pgp.py
connection_helper/sec.py
connection_helper/sql.py
connection_helper-0.13.1.dist-info/WHEEL
connection_helper-0.13.1.dist-info/METADATA
connection_helper-0.13.1.dist-info/RECORD
