Metadata-Version: 2.4
Name: connection-helper
Version: 0.13.1
Summary: A collection of helper for sql connections
Keywords: sql,duckdb,sqlite
Author: smeisegeier
Author-email: smeisegeier <dexterDSD@googlemail.com>
License-Expression: MIT
Classifier: License :: OSI Approved :: MIT License
Classifier: Programming Language :: Python :: 3
Classifier: Programming Language :: Python :: 3.11
Classifier: Development Status :: 4 - Beta
Classifier: Intended Audience :: Science/Research
Classifier: Operating System :: OS Independent
Classifier: Topic :: Scientific/Engineering
Requires-Dist: pandas>=2.0.0
Requires-Dist: pandas-plots
Requires-Dist: openpyxl
Requires-Dist: sqlalchemy>=2.0.28
Requires-Dist: sqlalchemy-utils>=0.41.2
Requires-Dist: python-gnupg>=0.5.2
Requires-Dist: duckdb>=1.3.0
Requires-Dist: numpy<2.0.0
Requires-Dist: pyodbc>=5.1.0
Requires-Dist: python-dotenv>=1.0.1
Requires-Dist: infisical-python>=2.2.3 ; extra == 'sec'
Requires-Dist: bitwarden-sdk ; extra == 'sec'
Requires-Python: >=3.11
Project-URL: Bug Tracker, https://github.com/smeisegeier/connection-helper/issues
Project-URL: Documentation, https://github.com/smeisegeier/connection-helper
Project-URL: Source Code, https://github.com/smeisegeier/connection-helper
Provides-Extra: sec
